metaplex_python-0.0.5.dist-info/METADATA
metaplex_python-0.0.5.dist-info/WHEEL
metaplex_python/__init__.py
metaplex_python/__init__.pyi
metaplex_python/py.typed
metaplex_python/metaplex_python.cpython-313-aarch64-linux-gnu.so
metaplex_python-0.0.5.dist-info/RECORD
