Metadata-Version: 2.4
Name: metaplex_python
Version: 0.0.5
Classifier: Programming Language :: Rust
Classifier: Programming Language :: Python :: Implementation :: CPython
Requires-Dist: hatch ; extra == 'dev'
Requires-Dist: maturin[patchelf] ; extra == 'dev'
Requires-Dist: pytest ; extra == 'dev'
Requires-Dist: solana ; extra == 'dev'
Requires-Dist: solders ; extra == 'dev'
Provides-Extra: dev
Summary: Python bindings for Solana Metaplex
Requires-Python: >=3.13.0
